ffscraper/Utils.py
ffscraper/__init__.py
ffscraper/__main__.py
ffscraper/AuthorScraper/__init__.py
ffscraper/AuthorScraper/beta.py
ffscraper/AuthorScraper/profile.py
ffscraper/FanFicScraper/__init__.py
ffscraper/FanFicScraper/metadata.py
ffscraper/FanFicScraper/review.py
ffscraper/FanFicScraper/story.py
ffscraper/tests/__init__.py
ffscraper/tests/tests.py
ffscraper/tests/ffscrapertests/__init__.py
ffscraper-0.1.2.dist-info/LICENSE.txt
ffscraper-0.1.2.dist-info/METADATA
ffscraper-0.1.2.dist-info/RECORD
ffscraper-0.1.2.dist-info/WHEEL
ffscraper-0.1.2.dist-info/top_level.txt
